{
  "id": "06a41f21-dcd6-4815-86dc-94e303deb64b",
  "prevId": "00000000-0000-0000-0000-000000000000",
  "version": "7",
  "dialect": "postgresql",
  "tables": {
    "public.contacts": {
      "name": "contacts",
      "schema": "",
      "columns": {
        "id": {
          "name": "id",
          "type": "serial",
          "primaryKey": true,
          "notNull": true
        },
        "name": {
          "name": "name",
          "type": "text",
          "primaryKey": false,
          "notNull": true
        },
        "email": {
          "name": "email",
          "type": "text",
          "primaryKey": false,
          "notNull": true
        },
        "subject": {
          "name": "subject",
          "type": "text",
          "primaryKey": false,
          "notNull": true
        },
        "message": {
          "name": "message",
          "type": "text",
          "primaryKey": false,
          "notNull": true
        },
        "status": {
          "name": "status",
          "type": "text",
          "primaryKey": false,
          "notNull": true,
          "default": "'unread'"
        },
        "created_at": {
          "name": "created_at",
          "type": "timestamp",
          "primaryKey": false,
          "notNull": false,
          "default": "now()"
        }
      },
      "indexes": {},
      "foreignKeys": {},
      "compositePrimaryKeys": {},
      "uniqueConstraints": {},
      "policies": {},
      "checkConstraints": {},
      "isRLSEnabled": false
    },
    "public.donations": {
      "name": "donations",
      "schema": "",
      "columns": {
        "id": {
          "name": "id",
          "type": "serial",
          "primaryKey": true,
          "notNull": true
        },
        "full_name": {
          "name": "full_name",
          "type": "text",
          "primaryKey": false,
          "notNull": true
        },
        "phone_number": {
          "name": "phone_number",
          "type": "text",
          "primaryKey": false,
          "notNull": true
        },
        "address": {
          "name": "address",
          "type": "text",
          "primaryKey": false,
          "notNull": true
        },
        "clothing_type": {
          "name": "clothing_type",
          "type": "text",
          "primaryKey": false,
          "notNull": true
        },
        "estimated_quantity": {
          "name": "estimated_quantity",
          "type": "text",
          "primaryKey": false,
          "notNull": true
        },
        "pickup_date": {
          "name": "pickup_date",
          "type": "text",
          "primaryKey": false,
          "notNull": true
        },
        "pickup_time": {
          "name": "pickup_time",
          "type": "text",
          "primaryKey": false,
          "notNull": true
        },
        "status": {
          "name": "status",
          "type": "text",
          "primaryKey": false,
          "notNull": true,
          "default": "'pending'"
        },
        "created_at": {
          "name": "created_at",
          "type": "timestamp",
          "primaryKey": false,
          "notNull": false,
          "default": "now()"
        }
      },
      "indexes": {},
      "foreignKeys": {},
      "compositePrimaryKeys": {},
      "uniqueConstraints": {},
      "policies": {},
      "checkConstraints": {},
      "isRLSEnabled": false
    },
    "public.news_articles": {
      "name": "news_articles",
      "schema": "",
      "columns": {
        "id": {
          "name": "id",
          "type": "serial",
          "primaryKey": true,
          "notNull": true
        },
        "title": {
          "name": "title",
          "type": "text",
          "primaryKey": false,
          "notNull": true
        },
        "excerpt": {
          "name": "excerpt",
          "type": "text",
          "primaryKey": false,
          "notNull": true
        },
        "content": {
          "name": "content",
          "type": "text",
          "primaryKey": false,
          "notNull": true
        },
        "category": {
          "name": "category",
          "type": "text",
          "primaryKey": false,
          "notNull": true
        },
        "image_url": {
          "name": "image_url",
          "type": "text",
          "primaryKey": false,
          "notNull": false
        },
        "published_at": {
          "name": "published_at",
          "type": "timestamp",
          "primaryKey": false,
          "notNull": false,
          "default": "now()"
        }
      },
      "indexes": {},
      "foreignKeys": {},
      "compositePrimaryKeys": {},
      "uniqueConstraints": {},
      "policies": {},
      "checkConstraints": {},
      "isRLSEnabled": false
    },
    "public.users": {
      "name": "users",
      "schema": "",
      "columns": {
        "id": {
          "name": "id",
          "type": "serial",
          "primaryKey": true,
          "notNull": true
        },
        "username": {
          "name": "username",
          "type": "text",
          "primaryKey": false,
          "notNull": true
        },
        "password": {
          "name": "password",
          "type": "text",
          "primaryKey": false,
          "notNull": true
        }
      },
      "indexes": {},
      "foreignKeys": {},
      "compositePrimaryKeys": {},
      "uniqueConstraints": {
        "users_username_unique": {
          "name": "users_username_unique",
          "nullsNotDistinct": false,
          "columns": [
            "username"
          ]
        }
      },
      "policies": {},
      "checkConstraints": {},
      "isRLSEnabled": false
    },
    "public.volunteers": {
      "name": "volunteers",
      "schema": "",
      "columns": {
        "id": {
          "name": "id",
          "type": "serial",
          "primaryKey": true,
          "notNull": true
        },
        "full_name": {
          "name": "full_name",
          "type": "text",
          "primaryKey": false,
          "notNull": true
        },
        "email": {
          "name": "email",
          "type": "text",
          "primaryKey": false,
          "notNull": true
        },
        "phone_number": {
          "name": "phone_number",
          "type": "text",
          "primaryKey": false,
          "notNull": true
        },
        "institution": {
          "name": "institution",
          "type": "text",
          "primaryKey": false,
          "notNull": false
        },
        "areas_of_interest": {
          "name": "areas_of_interest",
          "type": "text[]",
          "primaryKey": false,
          "notNull": false
        },
        "availability": {
          "name": "availability",
          "type": "text",
          "primaryKey": false,
          "notNull": true
        },
        "additional_comments": {
          "name": "additional_comments",
          "type": "text",
          "primaryKey": false,
          "notNull": false
        },
        "status": {
          "name": "status",
          "type": "text",
          "primaryKey": false,
          "notNull": true,
          "default": "'active'"
        },
        "created_at": {
          "name": "created_at",
          "type": "timestamp",
          "primaryKey": false,
          "notNull": false,
          "default": "now()"
        }
      },
      "indexes": {},
      "foreignKeys": {},
      "compositePrimaryKeys": {},
      "uniqueConstraints": {},
      "policies": {},
      "checkConstraints": {},
      "isRLSEnabled": false
    },
    "public.wall_locations": {
      "name": "wall_locations",
      "schema": "",
      "columns": {
        "id": {
          "name": "id",
          "type": "serial",
          "primaryKey": true,
          "notNull": true
        },
        "name": {
          "name": "name",
          "type": "text",
          "primaryKey": false,
          "notNull": true
        },
        "address": {
          "name": "address",
          "type": "text",
          "primaryKey": false,
          "notNull": true
        },
        "latitude": {
          "name": "latitude",
          "type": "text",
          "primaryKey": false,
          "notNull": false
        },
        "longitude": {
          "name": "longitude",
          "type": "text",
          "primaryKey": false,
          "notNull": false
        },
        "status": {
          "name": "status",
          "type": "text",
          "primaryKey": false,
          "notNull": true,
          "default": "'active'"
        },
        "last_restocked": {
          "name": "last_restocked",
          "type": "timestamp",
          "primaryKey": false,
          "notNull": false,
          "default": "now()"
        }
      },
      "indexes": {},
      "foreignKeys": {},
      "compositePrimaryKeys": {},
      "uniqueConstraints": {},
      "policies": {},
      "checkConstraints": {},
      "isRLSEnabled": false
    }
  },
  "enums": {},
  "schemas": {},
  "sequences": {},
  "roles": {},
  "policies": {},
  "views": {},
  "_meta": {
    "columns": {},
    "schemas": {},
    "tables": {}
  }
}